{
  "config": "{\"version\":\"5.51\",\"themeCollection\":{\"baseTheme\":{\"name\":\"CY24SU02\",\"version\":\"5.53\",\"type\":2}},\"activeSectionIndex\":0,\"defaultDrillFilterOtherVisuals\":true,\"slowDataSourceSettings\":{\"isCrossHighlightingDisabled\":false,\"isSlicerSelectionsButtonEnabled\":false,\"isFilterSelectionsButtonEnabled\":false,\"isFieldWellButtonEnabled\":false,\"isApplyAllButtonEnabled\":false},\"linguisticSchemaSyncVersion\":2,\"settings\":{\"useNewFilterPaneExperience\":true,\"allowChangeFilterTypes\":true,\"useStylableVisualContainerHeader\":true,\"queryLimitOption\":6,\"exportDataMode\":1,\"useDefaultAggregateDisplayName\":true},\"objects\":{\"section\":[{\"properties\":{\"verticalAlignment\":{\"expr\":{\"Literal\":{\"Value\":\"'Top'\"}}}}}]}}",
  "filters": "[{\"name\":\"Filter81431685cb603cd9e721\",\"expression\":{\"Column\":{\"Expression\":{\"SourceRef\":{\"Entity\":\"LA Crime Data\"}},\"Property\":\"UCR Reporting\"}},\"filter\":{\"Version\":2,\"From\":[{\"Name\":\"l\",\"Entity\":\"LA Crime Data\",\"Type\":0}],\"Where\":[{\"Condition\":{\"Not\":{\"Expression\":{\"Comparison\":{\"ComparisonKind\":0,\"Left\":{\"Column\":{\"Expression\":{\"SourceRef\":{\"Source\":\"l\"}},\"Property\":\"UCR Reporting\"}},\"Right\":{\"Literal\":{\"Value\":\"'PART II OFFENSE'\"}}}}}}}]},\"type\":\"Advanced\",\"howCreated\":1,\"isLockedInViewMode\":true}]",
  "layoutOptimization": 0,
  "resourcePackages": [
    {
      "resourcePackage": {
        "disabled": false,
        "items": [
          {
            "name": "CY24SU02",
            "path": "BaseThemes/CY24SU02.json",
            "type": 202
          }
        ],
        "name": "SharedResources",
        "type": 2
      }
    }
  ],
  "sections": [
    {
      "config": "{}",
      "displayName": "Crime Summary",
      "displayOption": 1,
      "filters": "[]",
      "height": 720.00,
      "name": "ReportSection",
      "visualContainers": [
        {
          "config": "{\"name\":\"0803693286baedd6591d\",\"layouts\":[{\"id\":0,\"position\":{\"x\":15.728740663940249,\"y\":648.0241153543383,\"z\":6000,\"width\":962.5989286331433,\"height\":64.48783672215502,\"tabOrder\":6000}}],\"singleVisual\":{\"visualType\":\"textbox\",\"drillFilterOtherVisuals\":true,\"objects\":{\"general\":[{\"properties\":{\"paragraphs\":[{\"textRuns\":[{\"value\":\"In \",\"textStyle\":{\"fontSize\":\"12pt\"}},{\"value\":{\"propertyIdentifier\":{\"objectName\":\"values\",\"propertyName\":\"expr\"},\"selector\":{\"id\":\"Area Name\"}},\"textStyle\":{\"fontSize\":\"12pt\"}},{\"value\":\", the average crime incidents occurred per day is \",\"textStyle\":{\"fontSize\":\"12pt\"}},{\"value\":{\"propertyIdentifier\":{\"objectName\":\"values\",\"propertyName\":\"expr\"},\"selector\":{\"id\":\"Avg. Crime\"}},\"textStyle\":{\"fontSize\":\"12pt\"}},{\"value\":\", with the most amount of crimes occurring at \",\"textStyle\":{\"fontSize\":\"12pt\"}},{\"value\":{\"propertyIdentifier\":{\"objectName\":\"values\",\"propertyName\":\"expr\"},\"selector\":{\"id\":\"Time with Most Crimes\"}},\"textStyle\":{\"fontSize\":\"12pt\"}},{\"value\":\". The top crime for this area is \",\"textStyle\":{\"fontSize\":\"12pt\"}},{\"value\":{\"propertyIdentifier\":{\"objectName\":\"values\",\"propertyName\":\"expr\"},\"selector\":{\"id\":\"Top Crime\"}},\"textStyle\":{\"fontSize\":\"12pt\"}},{\"value\":\", with a total of \",\"textStyle\":{\"fontSize\":\"12pt\"}},{\"value\":{\"propertyIdentifier\":{\"objectName\":\"values\",\"propertyName\":\"expr\"},\"selector\":{\"id\":\"Total Crime for Top Crime\"}},\"textStyle\":{\"fontSize\":\"12pt\"}},{\"value\":\" incidents, accounting for \",\"textStyle\":{\"fontSize\":\"12pt\"}},{\"value\":{\"propertyIdentifier\":{\"objectName\":\"values\",\"propertyName\":\"expr\"},\"selector\":{\"id\":\"Top Crime Percent\"}},\"textStyle\":{\"fontSize\":\"12pt\"}},{\"value\":\" of all crimes in this area\",\"textStyle\":{\"fontSize\":\"12pt\"}}]}]}}],\"values\":[{\"properties\":{\"expr\":{\"expr\":{\"Min\":{\"Expression\":{\"Column\":{\"Expression\":{\"Subquery\":{\"Query\":{\"Version\":2,\"From\":[{\"Name\":\"m\",\"Entity\":\"Measures Table\",\"Type\":0}],\"Select\":[{\"Measure\":{\"Expression\":{\"SourceRef\":{\"Source\":\"m\"}},\"Property\":\"Average Crime Recorded per Day\"},\"Name\":\"LA Crime Data.Average Crime Recorded per Day\"}]}}},\"Property\":\"LA Crime Data.Average Crime Recorded per Day\"}},\"IncludeAllTypes\":1},\"Annotations\":{\"NaturalLanguage\":{\"version\":1,\"kind\":\"NaturalLanguage\",\"annotation\":{\"name\":\"Avg. Crime\",\"utterance\":\"average crime recorded per day\"}}}}}},\"selector\":{\"id\":\"Avg. Crime\"}},{\"properties\":{\"expr\":{\"expr\":{\"Min\":{\"Expression\":{\"Column\":{\"Expression\":{\"Subquery\":{\"Query\":{\"Version\":2,\"From\":[{\"Name\":\"m\",\"Entity\":\"Measures Table\",\"Type\":0}],\"Select\":[{\"Measure\":{\"Expression\":{\"SourceRef\":{\"Source\":\"m\"}},\"Property\":\"Time with The Most Crime Recorded\"},\"Name\":\"LA Crime Data.Time with The Most Crime Recorded\"}]}}},\"Property\":\"LA Crime Data.Time with The Most Crime Recorded\"}},\"IncludeAllTypes\":1},\"Annotations\":{\"NaturalLanguage\":{\"version\":1,\"kind\":\"NaturalLanguage\",\"annotation\":{\"name\":\"Time with Most Crimes\",\"utterance\":\"time with the most crime recorded \"}}}}}},\"selector\":{\"id\":\"Time with Most Crimes\"}},{\"properties\":{\"expr\":{\"expr\":{\"Min\":{\"Expression\":{\"Column\":{\"Expression\":{\"Subquery\":{\"Query\":{\"Version\":2,\"From\":[{\"Name\":\"m\",\"Entity\":\"Measures Table\",\"Type\":0}],\"Select\":[{\"Measure\":{\"Expression\":{\"SourceRef\":{\"Source\":\"m\"}},\"Property\":\"Area Name\"},\"Name\":\"Measures Table.Area Name\"}]}}},\"Property\":\"Measures Table.Area Name\"}},\"IncludeAllTypes\":1},\"Annotations\":{\"NaturalLanguage\":{\"version\":1,\"kind\":\"NaturalLanguage\",\"annotation\":{\"name\":\"Area Name\",\"utterance\":\"Area Name\"}}}}}},\"selector\":{\"id\":\"Area Name\"}},{\"properties\":{\"expr\":{\"expr\":{\"Min\":{\"Expression\":{\"Column\":{\"Expression\":{\"Subquery\":{\"Query\":{\"Version\":2,\"From\":[{\"Name\":\"m\",\"Entity\":\"Measures Table\",\"Type\":0}],\"Select\":[{\"Measure\":{\"Expression\":{\"SourceRef\":{\"Source\":\"m\"}},\"Property\":\"Crime Type with The Most Crime Recorded\"},\"Name\":\"Measures Table.Crime Type with The Most Crime Recorded\"}]}}},\"Property\":\"Measures Table.Crime Type with The Most Crime Recorded\"}},\"IncludeAllTypes\":1},\"Annotations\":{\"NaturalLanguage\":{\"version\":1,\"kind\":\"NaturalLanguage\",\"annotation\":{\"name\":\"Top Crime\",\"utterance\":\"crime type with the most crime recorded\"}}}}}},\"selector\":{\"id\":\"Top Crime\"}},{\"properties\":{\"expr\":{\"expr\":{\"Min\":{\"Expression\":{\"Column\":{\"Expression\":{\"Subquery\":{\"Query\":{\"Version\":2,\"From\":[{\"Name\":\"m\",\"Entity\":\"Measures Table\",\"Type\":0}],\"Select\":[{\"Measure\":{\"Expression\":{\"SourceRef\":{\"Source\":\"m\"}},\"Property\":\"% Crime for Top Crime\"},\"Name\":\"Measures Table.% Crime for Top Crime\"}]}}},\"Property\":\"Measures Table.% Crime for Top Crime\"}},\"IncludeAllTypes\":1},\"Annotations\":{\"NaturalLanguage\":{\"version\":1,\"kind\":\"NaturalLanguage\",\"annotation\":{\"name\":\"Top Crime Percent\",\"utterance\":\"% crime for top crime\"}}}}},\"formatString\":{\"expr\":{\"Literal\":{\"Value\":\"'0.00 %;-0.00 %;0.00 %'\"}}}},\"selector\":{\"id\":\"Top Crime Percent\"}},{\"properties\":{\"expr\":{\"expr\":{\"Min\":{\"Expression\":{\"Column\":{\"Expression\":{\"Subquery\":{\"Query\":{\"Version\":2,\"From\":[{\"Name\":\"m\",\"Entity\":\"Measures Table\",\"Type\":0}],\"Select\":[{\"Measure\":{\"Expression\":{\"SourceRef\":{\"Source\":\"m\"}},\"Property\":\"Total Crime for Top Crime\"},\"Name\":\"Measures Table.Total Crime for Top Crime\"}]}}},\"Property\":\"Measures Table.Total Crime for Top Crime\"}},\"IncludeAllTypes\":1},\"Annotations\":{\"NaturalLanguage\":{\"version\":1,\"kind\":\"NaturalLanguage\",\"annotation\":{\"name\":\"Total Crime for Top Crime\",\"utterance\":\"total crime for top crime\"}}}}},\"formatString\":{\"expr\":{\"Literal\":{\"Value\":\"'#,0'\"}}}},\"selector\":{\"id\":\"Total Crime for Top Crime\"}}]}}}",
          "filters": "[]",
          "height": 64.49,
          "width": 962.60,
          "x": 15.73,
          "y": 648.02,
          "z": 6000.00
        },
        {
          "config": "{\"name\":\"12e6fe0ac21da5c1bb36\",\"layouts\":[{\"id\":0,\"position\":{\"x\":14.155866597546224,\"y\":14.155866597546224,\"z\":1000,\"width\":193.46351016646506,\"height\":72.35220705412515,\"tabOrder\":1000}}],\"singleVisual\":{\"visualType\":\"slicer\",\"projections\":{\"Values\":[{\"queryRef\":\"LA Crime Data.area_name\",\"active\":true}]},\"prototypeQuery\":{\"Version\":2,\"From\":[{\"Name\":\"c\",\"Entity\":\"LA Crime Data\",\"Type\":0}],\"Select\":[{\"Column\":{\"Expression\":{\"SourceRef\":{\"Source\":\"c\"}},\"Property\":\"Area Name\"},\"Name\":\"LA Crime Data.area_name\",\"NativeReferenceName\":\"Area Name\"}]},\"syncGroup\":{\"groupName\":\"AREA NAME\",\"fieldChanges\":true,\"filterChanges\":true},\"drillFilterOtherVisuals\":true,\"objects\":{\"data\":[{\"properties\":{\"mode\":{\"expr\":{\"Literal\":{\"Value\":\"'Dropdown'\"}}}}}],\"general\":[{\"properties\":{\"selfFilterEnabled\":{\"expr\":{\"Literal\":{\"Value\":\"true\"}}}}}]}}}",
          "filters": "[]",
          "height": 72.35,
          "width": 193.46,
          "x": 14.16,
          "y": 14.16,
          "z": 1000.00
        },
        {
          "config": "{\"name\":\"23bc74709870ad880875\",\"layouts\":[{\"id\":0,\"position\":{\"x\":15.728740663940249,\"y\":133.69429564349213,\"z\":7000,\"width\":1244.1433865176737,\"height\":91.22669585085345,\"tabOrder\":7000}}],\"singleVisual\":{\"visualType\":\"multiRowCard\",\"projections\":{\"Values\":[{\"queryRef\":\"LA Crime Data.Average Crime Recorded per Day\"},{\"queryRef\":\"LA Crime Data.Location with The Most Crime Recorded\"},{\"queryRef\":\"LA Crime Data.Time with The Most Crime Recorded\"}]},\"prototypeQuery\":{\"Version\":2,\"From\":[{\"Name\":\"m\",\"Entity\":\"Measures Table\",\"Type\":0}],\"Select\":[{\"Measure\":{\"Expression\":{\"SourceRef\":{\"Source\":\"m\"}},\"Property\":\"Average Crime Recorded per Day\"},\"Name\":\"LA Crime Data.Average Crime Recorded per Day\",\"NativeReferenceName\":\"Average Crime Recorded per Day\"},{\"Measure\":{\"Expression\":{\"SourceRef\":{\"Source\":\"m\"}},\"Property\":\"Crime Type with The Most Crime Recorded\"},\"Name\":\"LA Crime Data.Location with The Most Crime Recorded\",\"NativeReferenceName\":\"Crime Type with The Most Crime Recorded\"},{\"Measure\":{\"Expression\":{\"SourceRef\":{\"Source\":\"m\"}},\"Property\":\"Time with The Most Crime Recorded\"},\"Name\":\"LA Crime Data.Time with The Most Crime Recorded\",\"NativeReferenceName\":\"Time with The Most Crime Recorded\"}],\"OrderBy\":[{\"Direction\":2,\"Expression\":{\"Measure\":{\"Expression\":{\"SourceRef\":{\"Source\":\"m\"}},\"Property\":\"Average Crime Recorded per Day\"}}}]},\"drillFilterOtherVisuals\":true,\"hasDefaultSort\":true,\"objects\":{\"dataLabels\":[{\"properties\":{\"fontSize\":{\"expr\":{\"Literal\":{\"Value\":\"20D\"}}}}}]}}}",
          "filters": "[]",
          "height": 91.23,
          "width": 1244.14,
          "x": 15.73,
          "y": 133.69,
          "z": 7000.00
        },
        {
          "config": "{\"name\":\"40493982a866ae19332f\",\"layouts\":[{\"id\":0,\"position\":{\"x\":357.0487824684913,\"y\":249.60678730449243,\"z\":0,\"width\":526.9128122419984,\"height\":393.2185165985062,\"tabOrder\":0}}],\"singleVisual\":{\"visualType\":\"columnChart\",\"projections\":{\"Category\":[{\"queryRef\":\"Crime_Data_from_2020_to_Present.UCR Reporting\",\"active\":true}],\"Y\":[{\"queryRef\":\"Sum(LA Crime Data.dr_no)\"}]},\"prototypeQuery\":{\"Version\":2,\"From\":[{\"Name\":\"c\",\"Entity\":\"LA Crime Data\",\"Type\":0}],\"Select\":[{\"Column\":{\"Expression\":{\"SourceRef\":{\"Source\":\"c\"}},\"Property\":\"UCR Reporting\"},\"Name\":\"Crime_Data_from_2020_to_Present.UCR Reporting\",\"NativeReferenceName\":\"UCR Reporting\"},{\"Aggregation\":{\"Expression\":{\"Column\":{\"Expression\":{\"SourceRef\":{\"Source\":\"c\"}},\"Property\":\"Record Number\"}},\"Function\":2},\"Name\":\"Sum(LA Crime Data.dr_no)\",\"NativeReferenceName\":\"Count of Record Number\"}],\"OrderBy\":[{\"Direction\":2,\"Expression\":{\"Aggregation\":{\"Expression\":{\"Column\":{\"Expression\":{\"SourceRef\":{\"Source\":\"c\"}},\"Property\":\"Record Number\"}},\"Function\":2}}}]},\"drillFilterOtherVisuals\":true,\"hasDefaultSort\":true,\"objects\":{\"labels\":[{\"properties\":{\"show\":{\"expr\":{\"Literal\":{\"Value\":\"true\"}}},\"labelOverflow\":{\"expr\":{\"Literal\":{\"Value\":\"true\"}}},\"optimizeLabelDisplay\":{\"expr\":{\"Literal\":{\"Value\":\"true\"}}},\"labelDisplayUnits\":{\"expr\":{\"Literal\":{\"Value\":\"1D\"}}},\"enableDetailDataLabel\":{\"expr\":{\"Literal\":{\"Value\":\"false\"}}},\"detailLabelDisplayUnits\":{\"expr\":{\"Literal\":{\"Value\":\"1D\"}}}}},{\"properties\":{\"dynamicLabelDetail\":{\"expr\":{\"Aggregation\":{\"Expression\":{\"Column\":{\"Expression\":{\"SourceRef\":{\"Entity\":\"LA Crime Data\"}},\"Property\":\"DR_NO\"}},\"Function\":2}}}},\"selector\":{\"data\":[{\"dataViewWildcard\":{\"matchingOption\":1}}],\"highlightMatching\":1}}],\"totals\":[{\"properties\":{\"show\":{\"expr\":{\"Literal\":{\"Value\":\"true\"}}}}}],\"categoryAxis\":[{\"properties\":{\"showAxisTitle\":{\"expr\":{\"Literal\":{\"Value\":\"false\"}}}}}],\"valueAxis\":[{\"properties\":{\"showAxisTitle\":{\"expr\":{\"Literal\":{\"Value\":\"false\"}}},\"gridlineShow\":{\"expr\":{\"Literal\":{\"Value\":\"false\"}}}}}]},\"vcObjects\":{\"title\":[{\"properties\":{\"text\":{\"expr\":{\"Literal\":{\"Value\":\"'Total Incidents by Crime Type'\"}}}}}]}}}",
          "filters": "[]",
          "height": 393.22,
          "width": 526.91,
          "x": 357.05,
          "y": 249.61,
          "z": 0.00
        },
        {
          "config": "{\"name\":\"7f0acdef108a26a345cd\",\"layouts\":[{\"id\":0,\"position\":{\"x\":998.7750321602058,\"y\":648.0241153543383,\"z\":5000,\"width\":261.0970950214081,\"height\":64.48783672215502,\"tabOrder\":5000}}],\"singleVisual\":{\"visualType\":\"card\",\"projections\":{\"Values\":[{\"queryRef\":\"Min(Last Refreshed.Last Refreshed Date)\"}]},\"prototypeQuery\":{\"Version\":2,\"From\":[{\"Name\":\"l\",\"Entity\":\"Last Refreshed\",\"Type\":0}],\"Select\":[{\"Aggregation\":{\"Expression\":{\"Column\":{\"Expression\":{\"SourceRef\":{\"Source\":\"l\"}},\"Property\":\"Last Refreshed Date\"}},\"Function\":3},\"Name\":\"Min(Last Refreshed.Last Refreshed Date)\",\"NativeReferenceName\":\"Last Refreshed Date\"}],\"OrderBy\":[{\"Direction\":1,\"Expression\":{\"Aggregation\":{\"Expression\":{\"Column\":{\"Expression\":{\"SourceRef\":{\"Source\":\"l\"}},\"Property\":\"Last Refreshed Date\"}},\"Function\":3}}}]},\"columnProperties\":{\"Min(Last Refreshed.Last Refreshed Date)\":{\"displayName\":\"Last Refreshed Date\"}},\"drillFilterOtherVisuals\":true,\"hasDefaultSort\":true,\"objects\":{\"labels\":[{\"properties\":{\"fontSize\":{\"expr\":{\"Literal\":{\"Value\":\"20D\"}}}}}],\"categoryLabels\":[{\"properties\":{\"fontSize\":{\"expr\":{\"Literal\":{\"Value\":\"10D\"}}}}}]}}}",
          "filters": "[]",
          "height": 64.49,
          "width": 261.10,
          "x": 998.78,
          "y": 648.02,
          "z": 5000.00
        },
        {
          "config": "{\"name\":\"8e51fb662f712996f13e\",\"layouts\":[{\"id\":0,\"position\":{\"x\":892.1405110555542,\"y\":249.9213333175869,\"z\":4000,\"width\":368.0525315362018,\"height\":393.2185165985062,\"tabOrder\":4000}}],\"singleVisual\":{\"visualType\":\"pivotTable\",\"projections\":{\"Rows\":[{\"queryRef\":\"Crime_Data_from_2020_to_Present.UCR Reporting\",\"active\":true},{\"queryRef\":\"LA Crime Data.status_desc\",\"active\":true}],\"Values\":[{\"queryRef\":\"Sum(LA Crime Data.dr_no)\"},{\"queryRef\":\"Divide(Count(LA Crime Data.dr_no), ScopedEval(Count(LA Crime Data.dr_no), []))\"}]},\"prototypeQuery\":{\"Version\":2,\"From\":[{\"Name\":\"c\",\"Entity\":\"LA Crime Data\",\"Type\":0}],\"Select\":[{\"Column\":{\"Expression\":{\"SourceRef\":{\"Source\":\"c\"}},\"Property\":\"UCR Reporting\"},\"Name\":\"Crime_Data_from_2020_to_Present.UCR Reporting\",\"NativeReferenceName\":\"UCR Reporting\"},{\"Column\":{\"Expression\":{\"SourceRef\":{\"Source\":\"c\"}},\"Property\":\"status_desc\"},\"Name\":\"LA Crime Data.status_desc\",\"NativeReferenceName\":\"Status\"},{\"Aggregation\":{\"Expression\":{\"Column\":{\"Expression\":{\"SourceRef\":{\"Source\":\"c\"}},\"Property\":\"Record Number\"}},\"Function\":2},\"Name\":\"Sum(LA Crime Data.dr_no)\",\"NativeReferenceName\":\"Count of Record\"},{\"Arithmetic\":{\"Left\":{\"Aggregation\":{\"Expression\":{\"Column\":{\"Expression\":{\"SourceRef\":{\"Source\":\"c\"}},\"Property\":\"Record Number\"}},\"Function\":2}},\"Right\":{\"ScopedEval\":{\"Expression\":{\"Aggregation\":{\"Expression\":{\"Column\":{\"Expression\":{\"SourceRef\":{\"Source\":\"c\"}},\"Property\":\"Record Number\"}},\"Function\":2}},\"Scope\":[]}},\"Operator\":3},\"Name\":\"Divide(Count(LA Crime Data.dr_no), ScopedEval(Count(LA Crime Data.dr_no), []))\",\"NativeReferenceName\":\"% Total of Record\"}],\"OrderBy\":[{\"Direction\":1,\"Expression\":{\"Column\":{\"Expression\":{\"SourceRef\":{\"Source\":\"c\"}},\"Property\":\"UCR Reporting\"}}}]},\"expansionStates\":[{\"roles\":[\"Rows\"],\"levels\":[{\"queryRefs\":[\"Crime_Data_from_2020_to_Present.UCR Reporting\"],\"isPinned\":true},{\"queryRefs\":[\"LA Crime Data.status_desc\"],\"isCollapsed\":true,\"isPinned\":true}],\"root\":{\"identityValues\":null}}],\"columnProperties\":{\"LA Crime Data.status_desc\":{\"displayName\":\"Status\"},\"Sum(LA Crime Data.dr_no)\":{\"displayName\":\"Count of Record\"},\"Divide(Count(LA Crime Data.dr_no), ScopedEval(Count(LA Crime Data.dr_no), []))\":{\"displayName\":\"% Total of Record\"}},\"drillFilterOtherVisuals\":true,\"objects\":{\"columnWidth\":[{\"properties\":{\"value\":{\"expr\":{\"Literal\":{\"Value\":\"125.64461602615825D\"}}}},\"selector\":{\"metadata\":\"Crime_Data_from_2020_to_Present.UCR Reporting\"}},{\"properties\":{},\"selector\":{\"metadata\":\"Sum(LA Crime Data.dr_no)\"}}]},\"vcObjects\":{\"title\":[{\"properties\":{\"show\":{\"expr\":{\"Literal\":{\"Value\":\"true\"}}},\"text\":{\"expr\":{\"Literal\":{\"Value\":\"'Total Incidents by Crime Type and Status'\"}}}}}]}}}",
          "filters": "[]",
          "height": 393.22,
          "width": 368.05,
          "x": 892.14,
          "y": 249.92,
          "z": 4000.00
        },
        {
          "config": "{\"name\":\"c8e3061086bf52f7557f\",\"layouts\":[{\"id\":0,\"position\":{\"x\":15.735110060987932,\"y\":249.60678730449243,\"z\":2000,\"width\":333.4493020755333,\"height\":393.2185165985062,\"tabOrder\":2000}}],\"singleVisual\":{\"visualType\":\"map\",\"projections\":{\"X\":[{\"queryRef\":\"LA Crime Data.lon\"}],\"Y\":[{\"queryRef\":\"LA Crime Data.lat\"}],\"Size\":[{\"queryRef\":\"Sum(LA Crime Data.dr_no)\"}]},\"prototypeQuery\":{\"Version\":2,\"From\":[{\"Name\":\"c\",\"Entity\":\"LA Crime Data\",\"Type\":0}],\"Select\":[{\"Column\":{\"Expression\":{\"SourceRef\":{\"Source\":\"c\"}},\"Property\":\"lon\"},\"Name\":\"LA Crime Data.lon\",\"NativeReferenceName\":\"lon\"},{\"Column\":{\"Expression\":{\"SourceRef\":{\"Source\":\"c\"}},\"Property\":\"lat\"},\"Name\":\"LA Crime Data.lat\",\"NativeReferenceName\":\"lat\"},{\"Aggregation\":{\"Expression\":{\"Column\":{\"Expression\":{\"SourceRef\":{\"Source\":\"c\"}},\"Property\":\"Record Number\"}},\"Function\":2},\"Name\":\"Sum(LA Crime Data.dr_no)\",\"NativeReferenceName\":\"Count of Record Number\"}]},\"drillFilterOtherVisuals\":true,\"objects\":{\"mapStyles\":[{\"properties\":{\"mapTheme\":{\"expr\":{\"Literal\":{\"Value\":\"'grayscale'\"}}},\"showLabels\":{\"expr\":{\"Literal\":{\"Value\":\"true\"}}}}}],\"categoryLabels\":[{\"properties\":{\"show\":{\"expr\":{\"Literal\":{\"Value\":\"false\"}}}}}],\"heatMap\":[{\"properties\":{\"show\":{\"expr\":{\"Literal\":{\"Value\":\"true\"}}}}}]},\"vcObjects\":{\"title\":[{\"properties\":{\"text\":{\"expr\":{\"Literal\":{\"Value\":\"'Crime Heatmap'\"}}}}}]}}}",
          "filters": "[]",
          "height": 393.22,
          "width": 333.45,
          "x": 15.74,
          "y": 249.61,
          "z": 2000.00
        },
        {
          "config": "{\"name\":\"fd6dc885c4c4de636b02\",\"layouts\":[{\"id\":0,\"position\":{\"x\":1031.8053875544804,\"y\":14.155866597546224,\"z\":3000,\"width\":228.06673962713361,\"height\":102.23681431561161,\"tabOrder\":3000}}],\"singleVisual\":{\"visualType\":\"slicer\",\"projections\":{\"Values\":[{\"queryRef\":\"Calendar Table.Date\",\"active\":true}]},\"prototypeQuery\":{\"Version\":2,\"From\":[{\"Name\":\"c\",\"Entity\":\"Calendar Table\",\"Type\":0}],\"Select\":[{\"Column\":{\"Expression\":{\"SourceRef\":{\"Source\":\"c\"}},\"Property\":\"Date\"},\"Name\":\"Calendar Table.Date\",\"NativeReferenceName\":\"Date\"}],\"OrderBy\":[{\"Direction\":1,\"Expression\":{\"Column\":{\"Expression\":{\"SourceRef\":{\"Source\":\"c\"}},\"Property\":\"Date\"}}}]},\"syncGroup\":{\"groupName\":\"Date\",\"fieldChanges\":true,\"filterChanges\":true},\"drillFilterOtherVisuals\":true,\"hasDefaultSort\":true,\"objects\":{\"data\":[{\"properties\":{\"mode\":{\"expr\":{\"Literal\":{\"Value\":\"'Between'\"}}}}}],\"general\":[{\"properties\":{\"selfFilterEnabled\":{\"expr\":{\"Literal\":{\"Value\":\"true\"}}}}}]}}}",
          "filters": "[]",
          "height": 102.24,
          "width": 228.07,
          "x": 1031.81,
          "y": 14.16,
          "z": 3000.00
        }
      ],
      "width": 1280.00
    },
    {
      "config": "{}",
      "displayName": "Days to Report Crime",
      "displayOption": 1,
      "filters": "[]",
      "height": 720.00,
      "name": "ReportSection1b994158efea288ea54f",
      "ordinal": 2,
      "visualContainers": [
        {
          "config": "{\"name\":\"33bcbd5edd30a6064252\",\"layouts\":[{\"id\":0,\"position\":{\"x\":15.728740663940249,\"y\":622.8581302920338,\"z\":6000,\"width\":962.5989286331433,\"height\":89.65382178445942,\"tabOrder\":6000}}],\"singleVisual\":{\"visualType\":\"textbox\",\"drillFilterOtherVisuals\":true,\"objects\":{\"general\":[{\"properties\":{\"paragraphs\":[{\"textRuns\":[{\"value\":\"In \",\"textStyle\":{\"fontSize\":\"12pt\"}},{\"value\":{\"propertyIdentifier\":{\"objectName\":\"values\",\"propertyName\":\"expr\"},\"selector\":{\"id\":\"Area Name\"}},\"textStyle\":{\"fontSize\":\"12pt\"}},{\"value\":\", the top crime with the highest average of days reported after an incident is \",\"textStyle\":{\"fontSize\":\"12pt\"}},{\"value\":{\"propertyIdentifier\":{\"objectName\":\"values\",\"propertyName\":\"expr\"},\"selector\":{\"id\":\"Crime Type with Highest Avg. Days\"}},\"textStyle\":{\"fontSize\":\"12pt\"}},{\"value\":\", with an average of \",\"textStyle\":{\"fontSize\":\"12pt\"}},{\"value\":{\"propertyIdentifier\":{\"objectName\":\"values\",\"propertyName\":\"expr\"},\"selector\":{\"id\":\"Avg Days Reported for Top Crime\"}},\"textStyle\":{\"fontSize\":\"12pt\"}},{\"value\":\" days. Specifically,  \",\"textStyle\":{\"fontSize\":\"12pt\"}},{\"value\":{\"propertyIdentifier\":{\"objectName\":\"values\",\"propertyName\":\"expr\"},\"selector\":{\"id\":\"Crime Type with Highest Avg. Days\"}},\"textStyle\":{\"fontSize\":\"12pt\"}},{\"value\":\" victims of \",\"textStyle\":{\"fontSize\":\"12pt\"}},{\"value\":{\"propertyIdentifier\":{\"objectName\":\"values\",\"propertyName\":\"expr\"},\"selector\":{\"id\":\"Ethnicity with Highest Need\"}},\"textStyle\":{\"fontSize\":\"12pt\"}},{\"value\":\" descent with the highest record experience the highest need for tailoring strategies to improve response times and overall support for the victims by law enforcement and the community\",\"textStyle\":{\"fontSize\":\"12pt\"}}]}]}}],\"values\":[{\"properties\":{\"expr\":{\"expr\":{\"Min\":{\"Expression\":{\"Column\":{\"Expression\":{\"Subquery\":{\"Query\":{\"Version\":2,\"From\":[{\"Name\":\"m\",\"Entity\":\"Measures Table\",\"Type\":0}],\"Select\":[{\"Measure\":{\"Expression\":{\"SourceRef\":{\"Source\":\"m\"}},\"Property\":\"Average Crime Recorded per Day\"},\"Name\":\"LA Crime Data.Average Crime Recorded per Day\"}]}}},\"Property\":\"LA Crime Data.Average Crime Recorded per Day\"}},\"IncludeAllTypes\":1},\"Annotations\":{\"NaturalLanguage\":{\"version\":1,\"kind\":\"NaturalLanguage\",\"annotation\":{\"name\":\"Avg. Crime\",\"utterance\":\"average crime recorded per day\"}}}}}},\"selector\":{\"id\":\"Avg. Crime\"}},{\"properties\":{\"expr\":{\"expr\":{\"Min\":{\"Expression\":{\"Column\":{\"Expression\":{\"Subquery\":{\"Query\":{\"Version\":2,\"From\":[{\"Name\":\"m\",\"Entity\":\"Measures Table\",\"Type\":0}],\"Select\":[{\"Measure\":{\"Expression\":{\"SourceRef\":{\"Source\":\"m\"}},\"Property\":\"Time with The Most Crime Recorded\"},\"Name\":\"LA Crime Data.Time with The Most Crime Recorded\"}]}}},\"Property\":\"LA Crime Data.Time with The Most Crime Recorded\"}},\"IncludeAllTypes\":1},\"Annotations\":{\"NaturalLanguage\":{\"version\":1,\"kind\":\"NaturalLanguage\",\"annotation\":{\"name\":\"Time with Most Crimes\",\"utterance\":\"time with the most crime recorded \"}}}}}},\"selector\":{\"id\":\"Time with Most Crimes\"}},{\"properties\":{\"expr\":{\"expr\":{\"Min\":{\"Expression\":{\"Column\":{\"Expression\":{\"Subquery\":{\"Query\":{\"Version\":2,\"From\":[{\"Name\":\"m\",\"Entity\":\"Measures Table\",\"Type\":0}],\"Select\":[{\"Measure\":{\"Expression\":{\"SourceRef\":{\"Source\":\"m\"}},\"Property\":\"Area Name\"},\"Name\":\"Measures Table.Area Name\"}]}}},\"Property\":\"Measures Table.Area Name\"}},\"IncludeAllTypes\":1},\"Annotations\":{\"NaturalLanguage\":{\"version\":1,\"kind\":\"NaturalLanguage\",\"annotation\":{\"name\":\"Area Name\",\"utterance\":\"Area Name\"}}}}}},\"selector\":{\"id\":\"Area Name\"}},{\"properties\":{\"expr\":{\"expr\":{\"Min\":{\"Expression\":{\"Column\":{\"Expression\":{\"Subquery\":{\"Query\":{\"Version\":2,\"From\":[{\"Name\":\"m\",\"Entity\":\"Measures Table\",\"Type\":0}],\"Select\":[{\"Measure\":{\"Expression\":{\"SourceRef\":{\"Source\":\"m\"}},\"Property\":\"Crime Type with The Most Crime Recorded\"},\"Name\":\"Measures Table.Crime Type with The Most Crime Recorded\"}]}}},\"Property\":\"Measures Table.Crime Type with The Most Crime Recorded\"}},\"IncludeAllTypes\":1},\"Annotations\":{\"NaturalLanguage\":{\"version\":1,\"kind\":\"NaturalLanguage\",\"annotation\":{\"name\":\"Top Crime\",\"utterance\":\"crime type with the most crime recorded\"}}}}}},\"selector\":{\"id\":\"Top Crime\"}},{\"properties\":{\"expr\":{\"expr\":{\"Min\":{\"Expression\":{\"Column\":{\"Expression\":{\"Subquery\":{\"Query\":{\"Version\":2,\"From\":[{\"Name\":\"m\",\"Entity\":\"Measures Table\",\"Type\":0}],\"Select\":[{\"Measure\":{\"Expression\":{\"SourceRef\":{\"Source\":\"m\"}},\"Property\":\"% Crime for Top Crime\"},\"Name\":\"Measures Table.% Crime for Top Crime\"}]}}},\"Property\":\"Measures Table.% Crime for Top Crime\"}},\"IncludeAllTypes\":1},\"Annotations\":{\"NaturalLanguage\":{\"version\":1,\"kind\":\"NaturalLanguage\",\"annotation\":{\"name\":\"Top Crime Percent\",\"utterance\":\"% crime for top crime\"}}}}},\"formatString\":{\"expr\":{\"Literal\":{\"Value\":\"'0.00 %;-0.00 %;0.00 %'\"}}}},\"selector\":{\"id\":\"Top Crime Percent\"}},{\"properties\":{\"expr\":{\"expr\":{\"Min\":{\"Expression\":{\"Column\":{\"Expression\":{\"Subquery\":{\"Query\":{\"Version\":2,\"From\":[{\"Name\":\"m\",\"Entity\":\"Measures Table\",\"Type\":0}],\"Select\":[{\"Measure\":{\"Expression\":{\"SourceRef\":{\"Source\":\"m\"}},\"Property\":\"Total Crime for Top Crime\"},\"Name\":\"Measures Table.Total Crime for Top Crime\"}]}}},\"Property\":\"Measures Table.Total Crime for Top Crime\"}},\"IncludeAllTypes\":1},\"Annotations\":{\"NaturalLanguage\":{\"version\":1,\"kind\":\"NaturalLanguage\",\"annotation\":{\"name\":\"Total Crime for Top Crime\",\"utterance\":\"total crime for top crime\"}}}}},\"formatString\":{\"expr\":{\"Literal\":{\"Value\":\"'#,0'\"}}}},\"selector\":{\"id\":\"Total Crime for Top Crime\"}},{\"properties\":{\"expr\":{\"expr\":{\"Min\":{\"Expression\":{\"Column\":{\"Expression\":{\"Subquery\":{\"Query\":{\"Version\":2,\"From\":[{\"Name\":\"m\",\"Entity\":\"Measures Table\",\"Type\":0}],\"Select\":[{\"Measure\":{\"Expression\":{\"SourceRef\":{\"Source\":\"m\"}},\"Property\":\"Location with The Most Crime Recorded\"},\"Name\":\"Measures Table.Location with The Most Crime Recorded\"}]}}},\"Property\":\"Measures Table.Location with The Most Crime Recorded\"}},\"IncludeAllTypes\":1},\"Annotations\":{\"NaturalLanguage\":{\"version\":1,\"kind\":\"NaturalLanguage\",\"annotation\":{\"name\":\"Location for Top Crime\",\"utterance\":\"location with the most crime recorded\"}}}}}},\"selector\":{\"id\":\"Location for Top Crime\"}},{\"properties\":{\"expr\":{\"expr\":{\"Min\":{\"Expression\":{\"Column\":{\"Expression\":{\"Subquery\":{\"Query\":{\"Version\":2,\"From\":[{\"Name\":\"m\",\"Entity\":\"Measures Table\",\"Type\":0}],\"Select\":[{\"Measure\":{\"Expression\":{\"SourceRef\":{\"Source\":\"m\"}},\"Property\":\"Premise with The Most Crime Recorded\"},\"Name\":\"Measures Table.Premise with The Most Crime Recorded\"}]}}},\"Property\":\"Measures Table.Premise with The Most Crime Recorded\"}},\"IncludeAllTypes\":1},\"Annotations\":{\"NaturalLanguage\":{\"version\":1,\"kind\":\"NaturalLanguage\",\"annotation\":{\"name\":\"Premise with Top Crime\",\"utterance\":\"premise with the most crime recorded\"}}}}}},\"selector\":{\"id\":\"Premise with Top Crime\"}},{\"properties\":{\"expr\":{\"expr\":{\"Min\":{\"Expression\":{\"Column\":{\"Expression\":{\"Subquery\":{\"Query\":{\"Version\":2,\"From\":[{\"Name\":\"m\",\"Entity\":\"Measures Table\",\"Type\":0}],\"Select\":[{\"Measure\":{\"Expression\":{\"SourceRef\":{\"Source\":\"m\"}},\"Property\":\"Weapon Type with The Most Crime Recorded\"},\"Name\":\"Measures Table.Weapon Type with The Most Crime Recorded\"}]}}},\"Property\":\"Measures Table.Weapon Type with The Most Crime Recorded\"}},\"IncludeAllTypes\":1},\"Annotations\":{\"NaturalLanguage\":{\"version\":1,\"kind\":\"NaturalLanguage\",\"annotation\":{\"name\":\"Weapon with Top Crime\",\"utterance\":\"weapon type with the most crime recorded\"}}}}}},\"selector\":{\"id\":\"Weapon with Top Crime\"}},{\"properties\":{\"expr\":{\"expr\":{\"Min\":{\"Expression\":{\"Column\":{\"Expression\":{\"Subquery\":{\"Query\":{\"Version\":2,\"From\":[{\"Name\":\"m\",\"Entity\":\"Measures Table\",\"Type\":0}],\"Select\":[{\"Measure\":{\"Expression\":{\"SourceRef\":{\"Source\":\"m\"}},\"Property\":\"Crime Type with The Most Average Days Reported After Incident\"},\"Name\":\"Measures Table.Crime Type with The Most Average Days Reported After Incident\"}]}}},\"Property\":\"Measures Table.Crime Type with The Most Average Days Reported After Incident\"}},\"IncludeAllTypes\":1},\"Annotations\":{\"NaturalLanguage\":{\"version\":1,\"kind\":\"NaturalLanguage\",\"annotation\":{\"name\":\"Crime Type with Highest Avg. Days\",\"utterance\":\"crime type with the most average days reported after incident\"}}}}}},\"selector\":{\"id\":\"Crime Type with Highest Avg. Days\"}},{\"properties\":{\"expr\":{\"expr\":{\"Min\":{\"Expression\":{\"Column\":{\"Expression\":{\"Subquery\":{\"Query\":{\"Version\":2,\"From\":[{\"Name\":\"m\",\"Entity\":\"Measures Table\",\"Type\":0}],\"Select\":[{\"Measure\":{\"Expression\":{\"SourceRef\":{\"Source\":\"m\"}},\"Property\":\"Average Days Reported After Incident for Top Crime\"},\"Name\":\"Measures Table.Average Days Reported After Incident for Top Crime\"}]}}},\"Property\":\"Measures Table.Average Days Reported After Incident for Top Crime\"}},\"IncludeAllTypes\":1},\"Annotations\":{\"NaturalLanguage\":{\"version\":1,\"kind\":\"NaturalLanguage\",\"annotation\":{\"name\":\"Avg Days Reported for Top Crime\",\"utterance\":\"average days reported after incident for top crime\"}}}}}},\"selector\":{\"id\":\"Avg Days Reported for Top Crime\"}},{\"properties\":{\"expr\":{\"expr\":{\"Min\":{\"Expression\":{\"Column\":{\"Expression\":{\"Subquery\":{\"Query\":{\"Version\":2,\"From\":[{\"Name\":\"m\",\"Entity\":\"Measures Table\",\"Type\":0}],\"Select\":[{\"Measure\":{\"Expression\":{\"SourceRef\":{\"Source\":\"m\"}},\"Property\":\"Ethnicity Victims with High Crime Count and High Average Days to Report for Top Crime\"},\"Name\":\"Measures Table.Ethnicity Victims with High Crime Count and High Average Days to Report for Top Crime\"}]}}},\"Property\":\"Measures Table.Ethnicity Victims with High Crime Count and High Average Days to Report for Top Crime\"}},\"IncludeAllTypes\":1},\"Annotations\":{\"NaturalLanguage\":{\"version\":1,\"kind\":\"NaturalLanguage\",\"annotation\":{\"name\":\"Ethnicity with Highest Need\",\"utterance\":\"ethnicity victims with high crime count and high average days to report for top crime\"}}}}}},\"selector\":{\"id\":\"Ethnicity with Highest Need\"}}]}}}",
          "filters": "[]",
          "height": 89.65,
          "width": 962.60,
          "x": 15.73,
          "y": 622.86,
          "z": 6000.00
        },
        {
          "config": "{\"name\":\"3f42507c761547e3f1a0\",\"layouts\":[{\"id\":0,\"position\":{\"x\":475.0079680509955,\"y\":117.96555497955187,\"z\":3000,\"width\":363.33390933701975,\"height\":484.44521244935964,\"tabOrder\":3000}}],\"singleVisual\":{\"visualType\":\"pivotTable\",\"projections\":{\"Rows\":[{\"queryRef\":\"Crime_Data_from_2020_to_Present.UCR Reporting\",\"active\":true},{\"queryRef\":\"Crime_Data_from_2020_to_Present.Victim Descent\",\"active\":true}],\"Values\":[{\"queryRef\":\"Min(LA Crime Data.dr_no)\"},{\"queryRef\":\"Avg(Crime_Data_from_2020_to_Present.Days to Report)\"}]},\"prototypeQuery\":{\"Version\":2,\"From\":[{\"Name\":\"c\",\"Entity\":\"LA Crime Data\",\"Type\":0}],\"Select\":[{\"Column\":{\"Expression\":{\"SourceRef\":{\"Source\":\"c\"}},\"Property\":\"UCR Reporting\"},\"Name\":\"Crime_Data_from_2020_to_Present.UCR Reporting\",\"NativeReferenceName\":\"UCR Reporting\"},{\"Aggregation\":{\"Expression\":{\"Column\":{\"Expression\":{\"SourceRef\":{\"Source\":\"c\"}},\"Property\":\"Days to Report\"}},\"Function\":1},\"Name\":\"Avg(Crime_Data_from_2020_to_Present.Days to Report)\",\"NativeReferenceName\":\"Average Days Reported After Incident\"},{\"Column\":{\"Expression\":{\"SourceRef\":{\"Source\":\"c\"}},\"Property\":\"Victim Descent\"},\"Name\":\"Crime_Data_from_2020_to_Present.Victim Descent\",\"NativeReferenceName\":\"Victim Descent\"},{\"Aggregation\":{\"Expression\":{\"Column\":{\"Expression\":{\"SourceRef\":{\"Source\":\"c\"}},\"Property\":\"Record Number\"}},\"Function\":2},\"Name\":\"Min(LA Crime Data.dr_no)\",\"NativeReferenceName\":\"Count of Record\"}],\"OrderBy\":[{\"Direction\":2,\"Expression\":{\"Aggregation\":{\"Expression\":{\"Column\":{\"Expression\":{\"SourceRef\":{\"Source\":\"c\"}},\"Property\":\"Days to Report\"}},\"Function\":1}}}]},\"expansionStates\":[{\"roles\":[\"Rows\"],\"levels\":[{\"queryRefs\":[\"Crime_Data_from_2020_to_Present.UCR Reporting\"],\"isPinned\":true},{\"queryRefs\":[\"Crime_Data_from_2020_to_Present.Victim Descent\"],\"isCollapsed\":true,\"isPinned\":true}],\"root\":{\"identityValues\":null}}],\"columnProperties\":{\"Min(LA Crime Data.dr_no)\":{\"displayName\":\"Count of Record\"},\"Avg(Crime_Data_from_2020_to_Present.Days to Report)\":{\"displayName\":\"Average Days Reported After Incident\"}},\"drillFilterOtherVisuals\":true,\"hasDefaultSort\":true,\"objects\":{\"columnWidth\":[{\"properties\":{\"value\":{\"expr\":{\"Literal\":{\"Value\":\"133.54391340884223D\"}}}},\"selector\":{\"metadata\":\"Crime_Data_from_2020_to_Present.UCR Reporting\"}},{\"properties\":{\"value\":{\"expr\":{\"Literal\":{\"Value\":\"102.08504649556353D\"}}}},\"selector\":{\"metadata\":\"Avg(Crime_Data_from_2020_to_Present.Days to Report)\"}}]},\"vcObjects\":{\"title\":[{\"properties\":{\"show\":{\"expr\":{\"Literal\":{\"Value\":\"true\"}}},\"text\":{\"expr\":{\"Literal\":{\"Value\":\"'Average Days Reported After Incident by Crime Type and Ethnicity'\"}}}}}]}}}",
          "filters": "[]",
          "height": 484.45,
          "width": 363.33,
          "x": 475.01,
          "y": 117.97,
          "z": 3000.00
        },
        {
          "config": "{\"name\":\"6c75a396a298bbccbf2c\",\"layouts\":[{\"id\":0,\"position\":{\"x\":14.155866597546224,\"y\":117.96555497955187,\"z\":1000,\"width\":437.2589904575389,\"height\":484.44521244935964,\"tabOrder\":1000}}],\"singleVisual\":{\"visualType\":\"clusteredColumnChart\",\"projections\":{\"Y\":[{\"queryRef\":\"Sum(Crime_Data_from_2020_to_Present.Days to Report)\"}],\"Category\":[{\"queryRef\":\"Crime_Data_from_2020_to_Present.UCR Reporting\",\"active\":true}]},\"prototypeQuery\":{\"Version\":2,\"From\":[{\"Name\":\"c\",\"Entity\":\"LA Crime Data\",\"Type\":0}],\"Select\":[{\"Aggregation\":{\"Expression\":{\"Column\":{\"Expression\":{\"SourceRef\":{\"Source\":\"c\"}},\"Property\":\"Days to Report\"}},\"Function\":1},\"Name\":\"Sum(Crime_Data_from_2020_to_Present.Days to Report)\",\"NativeReferenceName\":\"Average of Days to Report\"},{\"Column\":{\"Expression\":{\"SourceRef\":{\"Source\":\"c\"}},\"Property\":\"UCR Reporting\"},\"Name\":\"Crime_Data_from_2020_to_Present.UCR Reporting\",\"NativeReferenceName\":\"UCR Reporting\"}],\"OrderBy\":[{\"Direction\":2,\"Expression\":{\"Aggregation\":{\"Expression\":{\"Column\":{\"Expression\":{\"SourceRef\":{\"Source\":\"c\"}},\"Property\":\"Days to Report\"}},\"Function\":1}}}]},\"drillFilterOtherVisuals\":true,\"hasDefaultSort\":true,\"objects\":{\"labels\":[{\"properties\":{\"show\":{\"expr\":{\"Literal\":{\"Value\":\"true\"}}}}}],\"valueAxis\":[{\"properties\":{\"gridlineShow\":{\"expr\":{\"Literal\":{\"Value\":\"false\"}}},\"showAxisTitle\":{\"expr\":{\"Literal\":{\"Value\":\"false\"}}}}}],\"categoryAxis\":[{\"properties\":{\"showAxisTitle\":{\"expr\":{\"Literal\":{\"Value\":\"false\"}}}}}]},\"vcObjects\":{\"title\":[{\"properties\":{\"text\":{\"expr\":{\"Literal\":{\"Value\":\"'Average Days Reported After Incident by Crime Type'\"}}}}}]}}}",
          "filters": "[]",
          "height": 484.45,
          "width": 437.26,
          "x": 14.16,
          "y": 117.97,
          "z": 1000.00
        },
        {
          "config": "{\"name\":\"9af49468c619a484dec2\",\"layouts\":[{\"id\":0,\"position\":{\"x\":14.155866597546224,\"y\":14.155866597546224,\"z\":0,\"width\":193.46351016646506,\"height\":72.35220705412515,\"tabOrder\":0}}],\"singleVisual\":{\"visualType\":\"slicer\",\"projections\":{\"Values\":[{\"queryRef\":\"LA Crime Data.area_name\",\"active\":true}]},\"prototypeQuery\":{\"Version\":2,\"From\":[{\"Name\":\"c\",\"Entity\":\"LA Crime Data\",\"Type\":0}],\"Select\":[{\"Column\":{\"Expression\":{\"SourceRef\":{\"Source\":\"c\"}},\"Property\":\"Area Name\"},\"Name\":\"LA Crime Data.area_name\",\"NativeReferenceName\":\"area_name\"}]},\"syncGroup\":{\"groupName\":\"AREA NAME\",\"fieldChanges\":true,\"filterChanges\":true},\"drillFilterOtherVisuals\":true,\"objects\":{\"data\":[{\"properties\":{\"mode\":{\"expr\":{\"Literal\":{\"Value\":\"'Dropdown'\"}}}}}],\"general\":[{\"properties\":{\"selfFilterEnabled\":{\"expr\":{\"Literal\":{\"Value\":\"true\"}}}}}]}}}",
          "filters": "[]",
          "height": 72.35,
          "width": 193.46,
          "x": 14.16,
          "y": 14.16,
          "z": 0.00
        },
        {
          "config": "{\"name\":\"acaa6f8157ca5b8178d6\",\"layouts\":[{\"id\":0,\"position\":{\"x\":998.7750321602058,\"y\":637.0139968895801,\"z\":5000,\"width\":261.0970950214081,\"height\":64.48783672215502,\"tabOrder\":5000}}],\"singleVisual\":{\"visualType\":\"card\",\"projections\":{\"Values\":[{\"queryRef\":\"Min(Last Refreshed.Last Refreshed Date)\"}]},\"prototypeQuery\":{\"Version\":2,\"From\":[{\"Name\":\"l\",\"Entity\":\"Last Refreshed\",\"Type\":0}],\"Select\":[{\"Aggregation\":{\"Expression\":{\"Column\":{\"Expression\":{\"SourceRef\":{\"Source\":\"l\"}},\"Property\":\"Last Refreshed Date\"}},\"Function\":3},\"Name\":\"Min(Last Refreshed.Last Refreshed Date)\",\"NativeReferenceName\":\"Last Refreshed Date\"}],\"OrderBy\":[{\"Direction\":1,\"Expression\":{\"Aggregation\":{\"Expression\":{\"Column\":{\"Expression\":{\"SourceRef\":{\"Source\":\"l\"}},\"Property\":\"Last Refreshed Date\"}},\"Function\":3}}}]},\"columnProperties\":{\"Min(Last Refreshed.Last Refreshed Date)\":{\"displayName\":\"Last Refreshed Date\"}},\"drillFilterOtherVisuals\":true,\"hasDefaultSort\":true,\"objects\":{\"labels\":[{\"properties\":{\"fontSize\":{\"expr\":{\"Literal\":{\"Value\":\"20D\"}}}}}],\"categoryLabels\":[{\"properties\":{\"fontSize\":{\"expr\":{\"Literal\":{\"Value\":\"10D\"}}}}}]}}}",
          "filters": "[]",
          "height": 64.49,
          "width": 261.10,
          "x": 998.78,
          "y": 637.01,
          "z": 5000.00
        },
        {
          "config": "{\"name\":\"e5b965baebc862cae9af\",\"layouts\":[{\"id\":0,\"position\":{\"x\":865.0807365167137,\"y\":117.96555497955187,\"z\":2000,\"width\":394.79139066490023,\"height\":484.44521244935964,\"tabOrder\":2000}}],\"singleVisual\":{\"visualType\":\"scatterChart\",\"projections\":{\"Y\":[{\"queryRef\":\"Crime_Data_from_2020_to_Present.Days to Report\"}],\"X\":[{\"queryRef\":\"Sum(LA Crime Data.vict_age)\",\"active\":true}]},\"prototypeQuery\":{\"Version\":2,\"From\":[{\"Name\":\"c\",\"Entity\":\"LA Crime Data\",\"Type\":0}],\"Select\":[{\"Column\":{\"Expression\":{\"SourceRef\":{\"Source\":\"c\"}},\"Property\":\"Days to Report\"},\"Name\":\"Crime_Data_from_2020_to_Present.Days to Report\",\"NativeReferenceName\":\"Days to Report\"},{\"Column\":{\"Expression\":{\"SourceRef\":{\"Source\":\"c\"}},\"Property\":\"Victim Age\"},\"Name\":\"Sum(LA Crime Data.vict_age)\",\"NativeReferenceName\":\"Victim Age\"}],\"OrderBy\":[{\"Direction\":2,\"Expression\":{\"Aggregation\":{\"Expression\":{\"Column\":{\"Expression\":{\"SourceRef\":{\"Source\":\"c\"}},\"Property\":\"Days to Report\"}},\"Function\":1}}}]},\"drillFilterOtherVisuals\":true,\"hasDefaultSort\":true,\"objects\":{\"trend\":[{\"properties\":{\"show\":{\"expr\":{\"Literal\":{\"Value\":\"true\"}}},\"displayName\":{\"expr\":{\"Literal\":{\"Value\":\"'Trend line 1'\"}}}}}],\"valueAxis\":[{\"properties\":{\"showAxisTitle\":{\"expr\":{\"Literal\":{\"Value\":\"false\"}}}}}],\"categoryAxis\":[{\"properties\":{\"showAxisTitle\":{\"expr\":{\"Literal\":{\"Value\":\"false\"}}}}}]},\"vcObjects\":{\"title\":[{\"properties\":{\"text\":{\"expr\":{\"Literal\":{\"Value\":\"'Days Reported After Incident by Victim Age'\"}}}}}]}}}",
          "filters": "[]",
          "height": 484.45,
          "width": 394.79,
          "x": 865.08,
          "y": 117.97,
          "z": 2000.00
        },
        {
          "config": "{\"name\":\"eec48312c47de9507e31\",\"layouts\":[{\"id\":0,\"position\":{\"x\":1031.8053875544804,\"y\":14.155866597546224,\"z\":4000,\"width\":228.06673962713361,\"height\":102.23681431561161,\"tabOrder\":4000}}],\"singleVisual\":{\"visualType\":\"slicer\",\"projections\":{\"Values\":[{\"queryRef\":\"Calendar Table.Date\",\"active\":true}]},\"prototypeQuery\":{\"Version\":2,\"From\":[{\"Name\":\"c\",\"Entity\":\"Calendar Table\",\"Type\":0}],\"Select\":[{\"Column\":{\"Expression\":{\"SourceRef\":{\"Source\":\"c\"}},\"Property\":\"Date\"},\"Name\":\"Calendar Table.Date\",\"NativeReferenceName\":\"Date\"}],\"OrderBy\":[{\"Direction\":1,\"Expression\":{\"Column\":{\"Expression\":{\"SourceRef\":{\"Source\":\"c\"}},\"Property\":\"Date\"}}}]},\"syncGroup\":{\"groupName\":\"Date\",\"fieldChanges\":true,\"filterChanges\":true},\"drillFilterOtherVisuals\":true,\"hasDefaultSort\":true,\"objects\":{\"data\":[{\"properties\":{\"mode\":{\"expr\":{\"Literal\":{\"Value\":\"'Between'\"}}}}}],\"general\":[{\"properties\":{\"selfFilterEnabled\":{\"expr\":{\"Literal\":{\"Value\":\"true\"}}}}}]}}}",
          "filters": "[]",
          "height": 102.24,
          "width": 228.07,
          "x": 1031.81,
          "y": 14.16,
          "z": 4000.00
        }
      ],
      "width": 1280.00
    },
    {
      "config": "{}",
      "displayName": "Crime Detailed",
      "displayOption": 1,
      "filters": "[{\"name\":\"Filtera0578422b5abb8c50786\",\"expression\":{\"Column\":{\"Expression\":{\"SourceRef\":{\"Entity\":\"LA Crime Data\"}},\"Property\":\"Weapon Type\"}},\"filter\":{\"Version\":2,\"From\":[{\"Name\":\"l\",\"Entity\":\"LA Crime Data\",\"Type\":0}],\"Where\":[{\"Condition\":{\"Not\":{\"Expression\":{\"Comparison\":{\"ComparisonKind\":0,\"Left\":{\"Column\":{\"Expression\":{\"SourceRef\":{\"Source\":\"l\"}},\"Property\":\"Weapon Type\"}},\"Right\":{\"Literal\":{\"Value\":\"null\"}}}}}}}]},\"type\":\"Advanced\",\"howCreated\":1,\"isLockedInViewMode\":true}]",
      "height": 720.00,
      "name": "ReportSection57657c6ae5379009e726",
      "ordinal": 1,
      "visualContainers": [
        {
          "config": "{\"name\":\"10aefe8bea8113e4ad9b\",\"layouts\":[{\"id\":0,\"position\":{\"x\":14.155866597546224,\"y\":14.155866597546224,\"z\":0,\"width\":193.46351016646506,\"height\":72.35220705412515,\"tabOrder\":0}}],\"singleVisual\":{\"visualType\":\"slicer\",\"projections\":{\"Values\":[{\"queryRef\":\"LA Crime Data.area_name\",\"active\":true}]},\"prototypeQuery\":{\"Version\":2,\"From\":[{\"Name\":\"c\",\"Entity\":\"LA Crime Data\",\"Type\":0}],\"Select\":[{\"Column\":{\"Expression\":{\"SourceRef\":{\"Source\":\"c\"}},\"Property\":\"Area Name\"},\"Name\":\"LA Crime Data.area_name\",\"NativeReferenceName\":\"area_name\"}]},\"syncGroup\":{\"groupName\":\"AREA NAME\",\"fieldChanges\":true,\"filterChanges\":true},\"drillFilterOtherVisuals\":true,\"objects\":{\"data\":[{\"properties\":{\"mode\":{\"expr\":{\"Literal\":{\"Value\":\"'Dropdown'\"}}}}}],\"general\":[{\"properties\":{\"selfFilterEnabled\":{\"expr\":{\"Literal\":{\"Value\":\"true\"}}}}}]}}}",
          "filters": "[]",
          "height": 72.35,
          "width": 193.46,
          "x": 14.16,
          "y": 14.16,
          "z": 0.00
        },
        {
          "config": "{\"name\":\"63c95cedd11696c447de\",\"layouts\":[{\"id\":0,\"position\":{\"x\":15.728740663940249,\"y\":648.0241153543383,\"z\":6000,\"width\":962.5989286331433,\"height\":64.48783672215502,\"tabOrder\":6000}}],\"singleVisual\":{\"visualType\":\"textbox\",\"drillFilterOtherVisuals\":true,\"objects\":{\"general\":[{\"properties\":{\"paragraphs\":[{\"textRuns\":[{\"value\":\"In \",\"textStyle\":{\"fontSize\":\"12pt\"}},{\"value\":{\"propertyIdentifier\":{\"objectName\":\"values\",\"propertyName\":\"expr\"},\"selector\":{\"id\":\"Area Name\"}},\"textStyle\":{\"fontSize\":\"12pt\"}},{\"value\":\", crimes are mostly occurring on \",\"textStyle\":{\"fontSize\":\"12pt\"}},{\"value\":{\"propertyIdentifier\":{\"objectName\":\"values\",\"propertyName\":\"expr\"},\"selector\":{\"id\":\"Premise with Top Crime\"}},\"textStyle\":{\"fontSize\":\"12pt\"}},{\"value\":\" , with most crimes occurring on \",\"textStyle\":{\"fontSize\":\"12pt\"}},{\"value\":{\"propertyIdentifier\":{\"objectName\":\"values\",\"propertyName\":\"expr\"},\"selector\":{\"id\":\"Location for Top Crime\"}},\"textStyle\":{\"fontSize\":\"12pt\"}},{\"value\":\". The most type of weapon being used is \",\"textStyle\":{\"fontSize\":\"12pt\"}},{\"value\":{\"propertyIdentifier\":{\"objectName\":\"values\",\"propertyName\":\"expr\"},\"selector\":{\"id\":\"Weapon with Top Crime\"}},\"textStyle\":{\"fontSize\":\"12pt\"}}]}]}}],\"values\":[{\"properties\":{\"expr\":{\"expr\":{\"Min\":{\"Expression\":{\"Column\":{\"Expression\":{\"Subquery\":{\"Query\":{\"Version\":2,\"From\":[{\"Name\":\"m\",\"Entity\":\"Measures Table\",\"Type\":0}],\"Select\":[{\"Measure\":{\"Expression\":{\"SourceRef\":{\"Source\":\"m\"}},\"Property\":\"Average Crime Recorded per Day\"},\"Name\":\"LA Crime Data.Average Crime Recorded per Day\"}]}}},\"Property\":\"LA Crime Data.Average Crime Recorded per Day\"}},\"IncludeAllTypes\":1},\"Annotations\":{\"NaturalLanguage\":{\"version\":1,\"kind\":\"NaturalLanguage\",\"annotation\":{\"name\":\"Avg. Crime\",\"utterance\":\"average crime recorded per day\"}}}}}},\"selector\":{\"id\":\"Avg. Crime\"}},{\"properties\":{\"expr\":{\"expr\":{\"Min\":{\"Expression\":{\"Column\":{\"Expression\":{\"Subquery\":{\"Query\":{\"Version\":2,\"From\":[{\"Name\":\"m\",\"Entity\":\"Measures Table\",\"Type\":0}],\"Select\":[{\"Measure\":{\"Expression\":{\"SourceRef\":{\"Source\":\"m\"}},\"Property\":\"Time with The Most Crime Recorded\"},\"Name\":\"LA Crime Data.Time with The Most Crime Recorded\"}]}}},\"Property\":\"LA Crime Data.Time with The Most Crime Recorded\"}},\"IncludeAllTypes\":1},\"Annotations\":{\"NaturalLanguage\":{\"version\":1,\"kind\":\"NaturalLanguage\",\"annotation\":{\"name\":\"Time with Most Crimes\",\"utterance\":\"time with the most crime recorded \"}}}}}},\"selector\":{\"id\":\"Time with Most Crimes\"}},{\"properties\":{\"expr\":{\"expr\":{\"Min\":{\"Expression\":{\"Column\":{\"Expression\":{\"Subquery\":{\"Query\":{\"Version\":2,\"From\":[{\"Name\":\"m\",\"Entity\":\"Measures Table\",\"Type\":0}],\"Select\":[{\"Measure\":{\"Expression\":{\"SourceRef\":{\"Source\":\"m\"}},\"Property\":\"Area Name\"},\"Name\":\"Measures Table.Area Name\"}]}}},\"Property\":\"Measures Table.Area Name\"}},\"IncludeAllTypes\":1},\"Annotations\":{\"NaturalLanguage\":{\"version\":1,\"kind\":\"NaturalLanguage\",\"annotation\":{\"name\":\"Area Name\",\"utterance\":\"Area Name\"}}}}}},\"selector\":{\"id\":\"Area Name\"}},{\"properties\":{\"expr\":{\"expr\":{\"Min\":{\"Expression\":{\"Column\":{\"Expression\":{\"Subquery\":{\"Query\":{\"Version\":2,\"From\":[{\"Name\":\"m\",\"Entity\":\"Measures Table\",\"Type\":0}],\"Select\":[{\"Measure\":{\"Expression\":{\"SourceRef\":{\"Source\":\"m\"}},\"Property\":\"Crime Type with The Most Crime Recorded\"},\"Name\":\"Measures Table.Crime Type with The Most Crime Recorded\"}]}}},\"Property\":\"Measures Table.Crime Type with The Most Crime Recorded\"}},\"IncludeAllTypes\":1},\"Annotations\":{\"NaturalLanguage\":{\"version\":1,\"kind\":\"NaturalLanguage\",\"annotation\":{\"name\":\"Top Crime\",\"utterance\":\"crime type with the most crime recorded\"}}}}}},\"selector\":{\"id\":\"Top Crime\"}},{\"properties\":{\"expr\":{\"expr\":{\"Min\":{\"Expression\":{\"Column\":{\"Expression\":{\"Subquery\":{\"Query\":{\"Version\":2,\"From\":[{\"Name\":\"m\",\"Entity\":\"Measures Table\",\"Type\":0}],\"Select\":[{\"Measure\":{\"Expression\":{\"SourceRef\":{\"Source\":\"m\"}},\"Property\":\"% Crime for Top Crime\"},\"Name\":\"Measures Table.% Crime for Top Crime\"}]}}},\"Property\":\"Measures Table.% Crime for Top Crime\"}},\"IncludeAllTypes\":1},\"Annotations\":{\"NaturalLanguage\":{\"version\":1,\"kind\":\"NaturalLanguage\",\"annotation\":{\"name\":\"Top Crime Percent\",\"utterance\":\"% crime for top crime\"}}}}},\"formatString\":{\"expr\":{\"Literal\":{\"Value\":\"'0.00 %;-0.00 %;0.00 %'\"}}}},\"selector\":{\"id\":\"Top Crime Percent\"}},{\"properties\":{\"expr\":{\"expr\":{\"Min\":{\"Expression\":{\"Column\":{\"Expression\":{\"Subquery\":{\"Query\":{\"Version\":2,\"From\":[{\"Name\":\"m\",\"Entity\":\"Measures Table\",\"Type\":0}],\"Select\":[{\"Measure\":{\"Expression\":{\"SourceRef\":{\"Source\":\"m\"}},\"Property\":\"Total Crime for Top Crime\"},\"Name\":\"Measures Table.Total Crime for Top Crime\"}]}}},\"Property\":\"Measures Table.Total Crime for Top Crime\"}},\"IncludeAllTypes\":1},\"Annotations\":{\"NaturalLanguage\":{\"version\":1,\"kind\":\"NaturalLanguage\",\"annotation\":{\"name\":\"Total Crime for Top Crime\",\"utterance\":\"total crime for top crime\"}}}}},\"formatString\":{\"expr\":{\"Literal\":{\"Value\":\"'#,0'\"}}}},\"selector\":{\"id\":\"Total Crime for Top Crime\"}},{\"properties\":{\"expr\":{\"expr\":{\"Min\":{\"Expression\":{\"Column\":{\"Expression\":{\"Subquery\":{\"Query\":{\"Version\":2,\"From\":[{\"Name\":\"m\",\"Entity\":\"Measures Table\",\"Type\":0}],\"Select\":[{\"Measure\":{\"Expression\":{\"SourceRef\":{\"Source\":\"m\"}},\"Property\":\"Location with The Most Crime Recorded\"},\"Name\":\"Measures Table.Location with The Most Crime Recorded\"}]}}},\"Property\":\"Measures Table.Location with The Most Crime Recorded\"}},\"IncludeAllTypes\":1},\"Annotations\":{\"NaturalLanguage\":{\"version\":1,\"kind\":\"NaturalLanguage\",\"annotation\":{\"name\":\"Location for Top Crime\",\"utterance\":\"location with the most crime recorded\"}}}}}},\"selector\":{\"id\":\"Location for Top Crime\"}},{\"properties\":{\"expr\":{\"expr\":{\"Min\":{\"Expression\":{\"Column\":{\"Expression\":{\"Subquery\":{\"Query\":{\"Version\":2,\"From\":[{\"Name\":\"m\",\"Entity\":\"Measures Table\",\"Type\":0}],\"Select\":[{\"Measure\":{\"Expression\":{\"SourceRef\":{\"Source\":\"m\"}},\"Property\":\"Premise with The Most Crime Recorded\"},\"Name\":\"Measures Table.Premise with The Most Crime Recorded\"}]}}},\"Property\":\"Measures Table.Premise with The Most Crime Recorded\"}},\"IncludeAllTypes\":1},\"Annotations\":{\"NaturalLanguage\":{\"version\":1,\"kind\":\"NaturalLanguage\",\"annotation\":{\"name\":\"Premise with Top Crime\",\"utterance\":\"premise with the most crime recorded\"}}}}}},\"selector\":{\"id\":\"Premise with Top Crime\"}},{\"properties\":{\"expr\":{\"expr\":{\"Min\":{\"Expression\":{\"Column\":{\"Expression\":{\"Subquery\":{\"Query\":{\"Version\":2,\"From\":[{\"Name\":\"m\",\"Entity\":\"Measures Table\",\"Type\":0}],\"Select\":[{\"Measure\":{\"Expression\":{\"SourceRef\":{\"Source\":\"m\"}},\"Property\":\"Weapon Type with The Most Crime Recorded\"},\"Name\":\"Measures Table.Weapon Type with The Most Crime Recorded\"}]}}},\"Property\":\"Measures Table.Weapon Type with The Most Crime Recorded\"}},\"IncludeAllTypes\":1},\"Annotations\":{\"NaturalLanguage\":{\"version\":1,\"kind\":\"NaturalLanguage\",\"annotation\":{\"name\":\"Weapon with Top Crime\",\"utterance\":\"weapon type with the most crime recorded\"}}}}}},\"selector\":{\"id\":\"Weapon with Top Crime\"}}]}}}",
          "filters": "[]",
          "height": 64.49,
          "width": 962.60,
          "x": 15.73,
          "y": 648.02,
          "z": 6000.00
        },
        {
          "config": "{\"name\":\"63cf3e9e48280c66a258\",\"layouts\":[{\"id\":0,\"position\":{\"x\":14.155866597546224,\"y\":86.50807365167137,\"z\":7000,\"width\":320.86630954438107,\"height\":119.53842904594589,\"tabOrder\":7000}}],\"singleVisual\":{\"visualType\":\"card\",\"projections\":{\"Values\":[{\"queryRef\":\"Measures Table.Location with The Most Crime Recorded\"}]},\"prototypeQuery\":{\"Version\":2,\"From\":[{\"Name\":\"m\",\"Entity\":\"Measures Table\",\"Type\":0}],\"Select\":[{\"Measure\":{\"Expression\":{\"SourceRef\":{\"Source\":\"m\"}},\"Property\":\"Location with The Most Crime Recorded\"},\"Name\":\"Measures Table.Location with The Most Crime Recorded\",\"NativeReferenceName\":\"Location Name with The Most Crime Recorded\"}]},\"columnProperties\":{\"Measures Table.Location with The Most Crime Recorded\":{\"displayName\":\"Location Name with The Most Crime Recorded\"}},\"drillFilterOtherVisuals\":true,\"objects\":{\"labels\":[{\"properties\":{\"fontSize\":{\"expr\":{\"Literal\":{\"Value\":\"20D\"}}}}}],\"categoryLabels\":[{\"properties\":{\"fontSize\":{\"expr\":{\"Literal\":{\"Value\":\"10D\"}}}}}]}}}",
          "filters": "[]",
          "height": 119.54,
          "width": 320.87,
          "x": 14.16,
          "y": 86.51,
          "z": 7000.00
        },
        {
          "config": "{\"name\":\"6e353c26bdd03a5d8b05\",\"layouts\":[{\"id\":0,\"position\":{\"x\":352.32379087226155,\"y\":116.39268091315785,\"z\":2000,\"width\":484.44521244935964,\"height\":503.31970124608796,\"tabOrder\":2000}}],\"singleVisual\":{\"visualType\":\"lineChart\",\"projections\":{\"Category\":[{\"queryRef\":\"LA Crime Data.date_occ\",\"active\":true}],\"Y\":[{\"queryRef\":\"CountNonNull(LA Crime Data.dr_no)\"}],\"Series\":[{\"queryRef\":\"LA Crime Data.weapon_desc\"}]},\"prototypeQuery\":{\"Version\":2,\"From\":[{\"Name\":\"c\",\"Entity\":\"LA Crime Data\",\"Type\":0}],\"Select\":[{\"Column\":{\"Expression\":{\"SourceRef\":{\"Source\":\"c\"}},\"Property\":\"date_occ\"},\"Name\":\"LA Crime Data.date_occ\",\"NativeReferenceName\":\"date_occ\"},{\"Aggregation\":{\"Expression\":{\"Column\":{\"Expression\":{\"SourceRef\":{\"Source\":\"c\"}},\"Property\":\"Record Number\"}},\"Function\":2},\"Name\":\"CountNonNull(LA Crime Data.dr_no)\",\"NativeReferenceName\":\"Count of dr_no1\"},{\"Column\":{\"Expression\":{\"SourceRef\":{\"Source\":\"c\"}},\"Property\":\"Weapon Type\"},\"Name\":\"LA Crime Data.weapon_desc\",\"NativeReferenceName\":\"Weapon Type\"}],\"OrderBy\":[{\"Direction\":1,\"Expression\":{\"Column\":{\"Expression\":{\"SourceRef\":{\"Source\":\"c\"}},\"Property\":\"date_occ\"}}}]},\"drillFilterOtherVisuals\":true,\"hasDefaultSort\":true,\"objects\":{\"labels\":[{\"properties\":{\"show\":{\"expr\":{\"Literal\":{\"Value\":\"true\"}}},\"optimizeLabelDisplay\":{\"expr\":{\"Literal\":{\"Value\":\"true\"}}},\"labelDisplayUnits\":{\"expr\":{\"Literal\":{\"Value\":\"1D\"}}}}}],\"categoryAxis\":[{\"properties\":{\"showAxisTitle\":{\"expr\":{\"Literal\":{\"Value\":\"false\"}}}}}],\"valueAxis\":[{\"properties\":{\"showAxisTitle\":{\"expr\":{\"Literal\":{\"Value\":\"false\"}}},\"gridlineShow\":{\"expr\":{\"Literal\":{\"Value\":\"false\"}}}}}]},\"vcObjects\":{\"title\":[{\"properties\":{\"text\":{\"expr\":{\"Literal\":{\"Value\":\"'Total Incidents Over Time by Top 5 Weapon Type'\"}}}}}]}}}",
          "filters": "[{\"name\":\"Filterb7169f045e88dd2ceb72\",\"expression\":{\"Column\":{\"Expression\":{\"SourceRef\":{\"Entity\":\"LA Crime Data\"}},\"Property\":\"Weapon Type\"}},\"filter\":{\"Version\":2,\"From\":[{\"Name\":\"subquery\",\"Expression\":{\"Subquery\":{\"Query\":{\"Version\":2,\"From\":[{\"Name\":\"c\",\"Entity\":\"LA Crime Data\",\"Type\":0}],\"Select\":[{\"Column\":{\"Expression\":{\"SourceRef\":{\"Source\":\"c\"}},\"Property\":\"Weapon Type\"},\"Name\":\"field\"}],\"OrderBy\":[{\"Direction\":2,\"Expression\":{\"Aggregation\":{\"Expression\":{\"Column\":{\"Expression\":{\"SourceRef\":{\"Source\":\"c\"}},\"Property\":\"Record Number\"}},\"Function\":2}}}],\"Top\":10}}},\"Type\":2},{\"Name\":\"c\",\"Entity\":\"LA Crime Data\",\"Type\":0}],\"Where\":[{\"Condition\":{\"In\":{\"Expressions\":[{\"Column\":{\"Expression\":{\"SourceRef\":{\"Source\":\"c\"}},\"Property\":\"Weapon Type\"}}],\"Table\":{\"SourceRef\":{\"Source\":\"subquery\"}}}}}]},\"type\":\"TopN\",\"howCreated\":0,\"isHiddenInViewMode\":false,\"isLockedInViewMode\":true}]",
          "height": 503.32,
          "width": 484.45,
          "x": 352.32,
          "y": 116.39,
          "z": 2000.00
        },
        {
          "config": "{\"name\":\"e10fa81942a156f4cf05\",\"layouts\":[{\"id\":0,\"position\":{\"x\":14.155866597546224,\"y\":221.7752433615575,\"z\":4000,\"width\":320.86630954438107,\"height\":397.9371387976883,\"tabOrder\":4000}}],\"singleVisual\":{\"visualType\":\"clusteredColumnChart\",\"projections\":{\"Category\":[{\"queryRef\":\"LA Crime Data.premis_desc\",\"active\":true}],\"Y\":[{\"queryRef\":\"CountNonNull(LA Crime Data.dr_no)\"}]},\"prototypeQuery\":{\"Version\":2,\"From\":[{\"Name\":\"c\",\"Entity\":\"LA Crime Data\",\"Type\":0}],\"Select\":[{\"Column\":{\"Expression\":{\"SourceRef\":{\"Source\":\"c\"}},\"Property\":\"premis_desc\"},\"Name\":\"LA Crime Data.premis_desc\",\"NativeReferenceName\":\"premis_desc\"},{\"Aggregation\":{\"Expression\":{\"Column\":{\"Expression\":{\"SourceRef\":{\"Source\":\"c\"}},\"Property\":\"Record Number\"}},\"Function\":2},\"Name\":\"CountNonNull(LA Crime Data.dr_no)\",\"NativeReferenceName\":\"Count of dr_no1\"}],\"OrderBy\":[{\"Direction\":2,\"Expression\":{\"Aggregation\":{\"Expression\":{\"Column\":{\"Expression\":{\"SourceRef\":{\"Source\":\"c\"}},\"Property\":\"Record Number\"}},\"Function\":2}}}]},\"drillFilterOtherVisuals\":true,\"hasDefaultSort\":true,\"objects\":{\"labels\":[{\"properties\":{\"show\":{\"expr\":{\"Literal\":{\"Value\":\"true\"}}},\"labelDisplayUnits\":{\"expr\":{\"Literal\":{\"Value\":\"1D\"}}}}}],\"valueAxis\":[{\"properties\":{\"showAxisTitle\":{\"expr\":{\"Literal\":{\"Value\":\"false\"}}},\"gridlineShow\":{\"expr\":{\"Literal\":{\"Value\":\"false\"}}}}}],\"categoryAxis\":[{\"properties\":{\"showAxisTitle\":{\"expr\":{\"Literal\":{\"Value\":\"false\"}}},\"concatenateLabels\":{\"expr\":{\"Literal\":{\"Value\":\"false\"}}}}}]},\"vcObjects\":{\"title\":[{\"properties\":{\"text\":{\"expr\":{\"Literal\":{\"Value\":\"'Top 10 Total Incidents by Location Type'\"}}}}}]}}}",
          "filters": "[{\"name\":\"Filterde1d8941648310d50580\",\"expression\":{\"Column\":{\"Expression\":{\"SourceRef\":{\"Entity\":\"LA Crime Data\"}},\"Property\":\"premis_desc\"}},\"filter\":{\"Version\":2,\"From\":[{\"Name\":\"subquery\",\"Expression\":{\"Subquery\":{\"Query\":{\"Version\":2,\"From\":[{\"Name\":\"c\",\"Entity\":\"LA Crime Data\",\"Type\":0}],\"Select\":[{\"Column\":{\"Expression\":{\"SourceRef\":{\"Source\":\"c\"}},\"Property\":\"premis_desc\"},\"Name\":\"field\"}],\"OrderBy\":[{\"Direction\":2,\"Expression\":{\"Aggregation\":{\"Expression\":{\"Column\":{\"Expression\":{\"SourceRef\":{\"Source\":\"c\"}},\"Property\":\"Record Number\"}},\"Function\":2}}}],\"Top\":10}}},\"Type\":2},{\"Name\":\"c\",\"Entity\":\"LA Crime Data\",\"Type\":0}],\"Where\":[{\"Condition\":{\"In\":{\"Expressions\":[{\"Column\":{\"Expression\":{\"SourceRef\":{\"Source\":\"c\"}},\"Property\":\"premis_desc\"}}],\"Table\":{\"SourceRef\":{\"Source\":\"subquery\"}}}}}]},\"type\":\"TopN\",\"howCreated\":0,\"isHiddenInViewMode\":false,\"isLockedInViewMode\":true}]",
          "height": 397.94,
          "width": 320.87,
          "x": 14.16,
          "y": 221.78,
          "z": 4000.00
        },
        {
          "config": "{\"name\":\"ea6ec8d8d845c45a11f1\",\"layouts\":[{\"id\":0,\"position\":{\"x\":1031.8053875544804,\"y\":14.155866597546224,\"z\":3000,\"width\":228.06673962713361,\"height\":102.23681431561161,\"tabOrder\":3000}}],\"singleVisual\":{\"visualType\":\"slicer\",\"projections\":{\"Values\":[{\"queryRef\":\"Calendar Table.Date\",\"active\":true}]},\"prototypeQuery\":{\"Version\":2,\"From\":[{\"Name\":\"c\",\"Entity\":\"Calendar Table\",\"Type\":0}],\"Select\":[{\"Column\":{\"Expression\":{\"SourceRef\":{\"Source\":\"c\"}},\"Property\":\"Date\"},\"Name\":\"Calendar Table.Date\",\"NativeReferenceName\":\"Date\"}],\"OrderBy\":[{\"Direction\":1,\"Expression\":{\"Column\":{\"Expression\":{\"SourceRef\":{\"Source\":\"c\"}},\"Property\":\"Date\"}}}]},\"syncGroup\":{\"groupName\":\"Date\",\"fieldChanges\":true,\"filterChanges\":true},\"drillFilterOtherVisuals\":true,\"hasDefaultSort\":true,\"objects\":{\"data\":[{\"properties\":{\"mode\":{\"expr\":{\"Literal\":{\"Value\":\"'Between'\"}}}}}],\"general\":[{\"properties\":{\"selfFilterEnabled\":{\"expr\":{\"Literal\":{\"Value\":\"true\"}}}}}]}}}",
          "filters": "[]",
          "height": 102.24,
          "width": 228.07,
          "x": 1031.81,
          "y": 14.16,
          "z": 3000.00
        },
        {
          "config": "{\"name\":\"eda3a44070531a30ba42\",\"layouts\":[{\"id\":0,\"position\":{\"x\":998.7750321602058,\"y\":648.0241153543383,\"z\":5000,\"width\":261.0970950214081,\"height\":64.48783672215502,\"tabOrder\":5000}}],\"singleVisual\":{\"visualType\":\"card\",\"projections\":{\"Values\":[{\"queryRef\":\"Min(Last Refreshed.Last Refreshed Date)\"}]},\"prototypeQuery\":{\"Version\":2,\"From\":[{\"Name\":\"l\",\"Entity\":\"Last Refreshed\",\"Type\":0}],\"Select\":[{\"Aggregation\":{\"Expression\":{\"Column\":{\"Expression\":{\"SourceRef\":{\"Source\":\"l\"}},\"Property\":\"Last Refreshed Date\"}},\"Function\":3},\"Name\":\"Min(Last Refreshed.Last Refreshed Date)\",\"NativeReferenceName\":\"Last Refreshed Date\"}],\"OrderBy\":[{\"Direction\":1,\"Expression\":{\"Aggregation\":{\"Expression\":{\"Column\":{\"Expression\":{\"SourceRef\":{\"Source\":\"l\"}},\"Property\":\"Last Refreshed Date\"}},\"Function\":3}}}]},\"columnProperties\":{\"Min(Last Refreshed.Last Refreshed Date)\":{\"displayName\":\"Last Refreshed Date\"}},\"drillFilterOtherVisuals\":true,\"hasDefaultSort\":true,\"objects\":{\"labels\":[{\"properties\":{\"fontSize\":{\"expr\":{\"Literal\":{\"Value\":\"20D\"}}}}}],\"categoryLabels\":[{\"properties\":{\"fontSize\":{\"expr\":{\"Literal\":{\"Value\":\"10D\"}}}}}]}}}",
          "filters": "[]",
          "height": 64.49,
          "width": 261.10,
          "x": 998.78,
          "y": 648.02,
          "z": 5000.00
        },
        {
          "config": "{\"name\":\"f1562a6f56d02dc2687c\",\"layouts\":[{\"id\":0,\"position\":{\"x\":852.4977439855614,\"y\":116.39268091315785,\"z\":1000,\"width\":407.37438319605246,\"height\":503.31970124608796,\"tabOrder\":1000}}],\"singleVisual\":{\"visualType\":\"treemap\",\"projections\":{\"Values\":[{\"queryRef\":\"CountNonNull(LA Crime Data.dr_no)\"}],\"Group\":[{\"queryRef\":\"LA Crime Data.UCR Reporting\",\"active\":true}],\"Details\":[{\"queryRef\":\"LA Crime Data.Weapon Type\"}]},\"prototypeQuery\":{\"Version\":2,\"From\":[{\"Name\":\"c\",\"Entity\":\"LA Crime Data\",\"Type\":0}],\"Select\":[{\"Aggregation\":{\"Expression\":{\"Column\":{\"Expression\":{\"SourceRef\":{\"Source\":\"c\"}},\"Property\":\"Record Number\"}},\"Function\":2},\"Name\":\"CountNonNull(LA Crime Data.dr_no)\",\"NativeReferenceName\":\"Count of dr_no1\"},{\"Column\":{\"Expression\":{\"SourceRef\":{\"Source\":\"c\"}},\"Property\":\"UCR Reporting\"},\"Name\":\"LA Crime Data.UCR Reporting\",\"NativeReferenceName\":\"UCR Reporting\"},{\"Column\":{\"Expression\":{\"SourceRef\":{\"Source\":\"c\"}},\"Property\":\"Weapon Type\"},\"Name\":\"LA Crime Data.Weapon Type\",\"NativeReferenceName\":\"Weapon Type\"}],\"OrderBy\":[{\"Direction\":2,\"Expression\":{\"Aggregation\":{\"Expression\":{\"Column\":{\"Expression\":{\"SourceRef\":{\"Source\":\"c\"}},\"Property\":\"DR_NO\"}},\"Function\":2}}}]},\"drillFilterOtherVisuals\":true,\"hasDefaultSort\":true,\"objects\":{\"labels\":[{\"properties\":{\"show\":{\"expr\":{\"Literal\":{\"Value\":\"true\"}}},\"labelDisplayUnits\":{\"expr\":{\"Literal\":{\"Value\":\"1D\"}}}}}],\"categoryLabels\":[{\"properties\":{\"show\":{\"expr\":{\"Literal\":{\"Value\":\"true\"}}}}}],\"legend\":[{\"properties\":{\"show\":{\"expr\":{\"Literal\":{\"Value\":\"false\"}}}}}]},\"vcObjects\":{\"title\":[{\"properties\":{\"text\":{\"expr\":{\"Literal\":{\"Value\":\"'Top 5 Weapons Used by Serious Crime'\"}}}}}],\"visualHeader\":[{\"properties\":{\"show\":{\"expr\":{\"Literal\":{\"Value\":\"true\"}}}}}]}}}",
          "filters": "[{\"name\":\"Filter7b614f993a8ae7dbc8d4\",\"expression\":{\"Column\":{\"Expression\":{\"SourceRef\":{\"Entity\":\"LA Crime Data\"}},\"Property\":\"Weapon Type\"}},\"filter\":{\"Version\":2,\"From\":[{\"Name\":\"subquery\",\"Expression\":{\"Subquery\":{\"Query\":{\"Version\":2,\"From\":[{\"Name\":\"l\",\"Entity\":\"LA Crime Data\",\"Type\":0}],\"Select\":[{\"Column\":{\"Expression\":{\"SourceRef\":{\"Source\":\"l\"}},\"Property\":\"Weapon Type\"},\"Name\":\"field\"}],\"OrderBy\":[{\"Direction\":2,\"Expression\":{\"Aggregation\":{\"Expression\":{\"Column\":{\"Expression\":{\"SourceRef\":{\"Source\":\"l\"}},\"Property\":\"Record Number\"}},\"Function\":2}}}],\"Top\":5}}},\"Type\":2},{\"Name\":\"l\",\"Entity\":\"LA Crime Data\",\"Type\":0}],\"Where\":[{\"Condition\":{\"In\":{\"Expressions\":[{\"Column\":{\"Expression\":{\"SourceRef\":{\"Source\":\"l\"}},\"Property\":\"Weapon Type\"}}],\"Table\":{\"SourceRef\":{\"Source\":\"subquery\"}}}}}]},\"type\":\"TopN\",\"howCreated\":1},{\"name\":\"Filtera998266fc2ab18b8080a\",\"expression\":{\"Column\":{\"Expression\":{\"SourceRef\":{\"Entity\":\"LA Crime Data\"}},\"Property\":\"UCR Reporting\"}},\"filter\":{\"Version\":2,\"From\":[{\"Name\":\"l\",\"Entity\":\"LA Crime Data\",\"Type\":0}],\"Where\":[{\"Condition\":{\"In\":{\"Expressions\":[{\"Column\":{\"Expression\":{\"SourceRef\":{\"Source\":\"l\"}},\"Property\":\"UCR Reporting\"}}],\"Values\":[[{\"Literal\":{\"Value\":\"'HOMICIDE'\"}}],[{\"Literal\":{\"Value\":\"'RAPE'\"}}],[{\"Literal\":{\"Value\":\"'ROBBERY'\"}}],[{\"Literal\":{\"Value\":\"'AGG. ASSAULTS'\"}}]]}}}]},\"type\":\"Categorical\",\"howCreated\":0,\"objects\":{},\"isHiddenInViewMode\":false}]",
          "height": 503.32,
          "width": 407.37,
          "x": 852.50,
          "y": 116.39,
          "z": 1000.00
        }
      ],
      "width": 1280.00
    }
  ]
}